pretty_good_diff/__init__.py
pretty_good_diff/colors.py
pretty_good_diff/diff.py
pretty_good_diff/exceptions.py
pretty_good_diff/output.py
pretty_good_diff/sentinel.py
tests/__init__.py
tests/test_diff.py
tests/test_output.py
pretty_good_diff-0.1.0.dist-info/LICENSE.txt
pretty_good_diff-0.1.0.dist-info/METADATA
pretty_good_diff-0.1.0.dist-info/WHEEL
pretty_good_diff-0.1.0.dist-info/top_level.txt
pretty_good_diff-0.1.0.dist-info/RECORD
