Metadata-Version: 2.1
Name: pretty-good-diff
Version: 0.1.0
Summary: Gives you a pretty good diff between two objects
Home-page: https://github.com/Viktor-Bubanja/pretty-good-diff
Author: Viktor Bubanja
Author-email: viktor.bubanja@hotmail.com
Project-URL: repository, https://github.com/Viktor-Bubanja/pretty-good-diff
Keywords: diff,difference,checker,highlight,color,colour,colored,coloured
Classifier: Programming Language :: Python :: 3
Classifier: License :: OSI Approved :: MIT License
Classifier: Operating System :: OS Independent
Requires-Python: >=3.9
License-File: LICENSE.txt
Provides-Extra: test
Requires-Dist: pytest ; extra == 'test'
